commonroad_rp/__init__.py
commonroad_rp/cost_function.py
commonroad_rp/polynomial_trajectory.py
commonroad_rp/reactive_planner.py
commonroad_rp/sampling/__init__.py
commonroad_rp/sampling/base/__init__.py
commonroad_rp/sampling/base/base_sampling_domain.py
commonroad_rp/sampling/base/base_sampling_space.py
commonroad_rp/sampling/factory.py
commonroad_rp/sampling/implementation/__init__.py
commonroad_rp/sampling/implementation/sampling_domain.py
commonroad_rp/sampling/implementation/sampling_space_corridor.py
commonroad_rp/sampling/implementation/sampling_space_fixed.py
commonroad_rp/state.py
commonroad_rp/trajectories.py
commonroad_rp/utility/__init__.py
commonroad_rp/utility/config.py
commonroad_rp/utility/evaluation.py
commonroad_rp/utility/general.py
commonroad_rp/utility/logger.py
commonroad_rp/utility/utils_coordinate_system.py
commonroad_rp/utility/visualization.py
commonroad_reactive_planner-2025.1.dist-info/LICENSE
commonroad_reactive_planner-2025.1.dist-info/METADATA
commonroad_reactive_planner-2025.1.dist-info/WHEEL
commonroad_reactive_planner-2025.1.dist-info/RECORD
