Metadata-Version: 2.3
Name: commonroad-reactive-planner
Version: 2025.1
Summary: CommonRoad Reactive Planner: Sampling-based Frenet Planner
License: BSD
Keywords: autonomous,automated,vehicles,driving,motion,planning
Author: Cyber-Physical Systems Group, Technical University of Munich
Author-email: commonroad@lists.lrz.de
Requires-Python: >=3.9,<3.12
Classifier: License :: OSI Approved :: BSD License
Classifier: License :: Other/Proprietary License
Classifier: Operating System :: POSIX :: Linux
Classifier: Programming Language :: Python :: 3
Classifier: Programming Language :: Python :: 3.9
Classifier: Programming Language :: Python :: 3.10
Classifier: Programming Language :: Python :: 3.11
Classifier: Programming Language :: Python :: 3.8
Requires-Dist: commonroad-clcs (>=2025.1.1,<2026.0.0)
Requires-Dist: commonroad-drivability-checker (>=2025.1,<2026.0)
Requires-Dist: commonroad-io (>=2024.3,<2025.0)
Requires-Dist: commonroad-route-planner (>=2025.1.0,<2026.0.0)
Requires-Dist: commonroad_vehicle_models (>=3.0.2)
Requires-Dist: imageio (>=2.13.5)
Requires-Dist: matplotlib (>=2.2.2)
Requires-Dist: methodtools (>=0.4.5,<0.5.0)
Requires-Dist: networkx (>=2.2)
Requires-Dist: numpy (>=1.22)
Requires-Dist: omegaconf (>=2.1.1)
Requires-Dist: scipy (>=1.5.2)
Requires-Dist: triangle (>=20230923)
Project-URL: Homepage, https://commonroad.in.tum.de
Project-URL: Source, https://gitlab.lrz.de/tum-cps/commonroad-reactive-planner
